fontdiffenator-0.1.1.dist-info/RECORD
fontdiffenator-0.1.1.dist-info/metadata.json
fontdiffenator-0.1.1.dist-info/WHEEL
fontdiffenator-0.1.1.dist-info/entry_points.txt
fontdiffenator-0.1.1.dist-info/DESCRIPTION.rst
fontdiffenator-0.1.1.dist-info/top_level.txt
fontdiffenator-0.1.1.dist-info/METADATA
diffenator/metrics.py
diffenator/kerning.py
diffenator/hbinput.py
diffenator/__init__.py
diffenator/dumper.py
diffenator/font.py
diffenator/names.py
diffenator/marks.py
diffenator/utils.py
diffenator/attribs.py
diffenator/diff.py
diffenator/glyphs.py
diffenator/__main__.py
